agstools/__init__.py
agstools/_agstools.py
agstools/_helpers.py
agstools/_storenamevaluepairs.py
agstools/_version.py
agstools/agsadmin/__init__.py
agstools/agsadmin/_agsadmin.py
agstools/agsadmin/_delete.py
agstools/agsadmin/_machine_start.py
agstools/agsadmin/_machine_stop.py
agstools/agsadmin/_rest_helpers.py
agstools/agsadmin/_service_delete.py
agstools/agsadmin/_service_start.py
agstools/agsadmin/_service_stop.py
agstools/agsadmin/_start.py
agstools/agsadmin/_stop.py
agstools/arcpy/__init__.py
agstools/arcpy/_agsconn.py
agstools/arcpy/_dbconn.py
agstools/arcpy/_helpers.py
agstools/arcpy/_locator.py
agstools/arcpy/_set_sde_permissions.py
agstools/arcpyext/__init__.py
agstools/arcpyext/_copy.py
agstools/arcpyext/_gpsddraft.py
agstools/arcpyext/_helpers.py
agstools/arcpyext/_imagesddraft.py
agstools/arcpyext/_multiupdatedata.py
agstools/arcpyext/_publish.py
agstools/arcpyext/_schematransform.py
agstools/arcpyext/_sd.py
agstools/arcpyext/_sddraft.py
agstools/arcpyext/_updatedata.py
agstools-0.4.2.dist-info/DESCRIPTION.rst
agstools-0.4.2.dist-info/METADATA
agstools-0.4.2.dist-info/RECORD
agstools-0.4.2.dist-info/WHEEL
agstools-0.4.2.dist-info/entry_points.txt
agstools-0.4.2.dist-info/metadata.json
agstools-0.4.2.dist-info/top_level.txt
agstools-0.4.2.dist-info/zip-safe
