Metadata-Version: 2.0
Name: agstools
Version: 0.4.2
Summary: ArcGIS Server 10.1+ Administrative Command-Line Tools
Home-page: https://github.com/DavidWhittingham/agstools
Author: David Whittingham; Adam Kerz; Daniel Baternik
Author-email: UNKNOWN
License: BSD 3-Clause
Keywords: arcgis esri
Platform: UNKNOWN
Classifier: Development Status :: 4 - Beta
Classifier: Intended Audience :: Developers
Classifier: Natural Language :: English
Classifier: License :: OSI Approved :: BSD License
Classifier: Programming Language :: Python :: 2.7
Requires-Dist: agsadmin (>=0.1.2)
Requires-Dist: future (>=0.15.2)
